license.S.HTML
venue.S.HTML
biotech/BrightAgrotech--vertical-farm-916337_1920.jpg
biotech/___itinerary/itinerary - breaking.S.HTML
biotech/___itinerary/itinerary.S.HTML
biotech/___itinerary/maybes.s.HTML
biotech/___itinerary/processes/errout/script.py
biotech/___itinerary/processes/errout/start.py
biotech/___itinerary/processes/errout_v1/script.py
biotech/___itinerary/processes/errout_v1/start.py
biotech/___itinerary/processes/errout_v2/script.py
biotech/___itinerary/processes/errout_v2/start.py
biotech/__glossary/biotech_1
biotech/__glossary/glossary.S.HTML
biotech/__init__.py
biotech/__license/options/gpl-3.0-standalone.html
biotech/_book/advanced tutorial.s.HTML
biotech/_book/book.s.HTML
biotech/_book/relevant.s.HTML
biotech/_clique/__init__.py
biotech/_clique/group/__init__.py
biotech/_status/DB/records.json
biotech/_status/establish.py
biotech/_status/monitors/-01_start/chassis/modules/monitor_1.py
biotech/_status/monitors/-01_start/status_1.py
biotech/_status/monitors/00_start/chassis/modules/monitor_1.py
biotech/_status/monitors/00_start/status_1.py
biotech/_status/monitors/01/stasis/path_1_health.py
biotech/_status/monitors/01/stasis/path_2_health.py
biotech/_status/monitors/01/status_1.py
biotech/_status/monitors/02/stasis/1_health.py
biotech/_status/monitors/02/stasis/2_health.py
biotech/_status/monitors/02/stasis/modules/MODULE_1.py
biotech/_status/monitors/02/status_1.py
biotech/_status/monitors/03_empty_glob/status_1.py
biotech/_status/monitors/04.0_bad_import/stasis/1_health.py
biotech/_status/monitors/04.0_bad_import/status_1.py
biotech/_status/monitors/04.1_bad_import/stasis/1_health.py
biotech/_status/monitors/04.1_bad_import/status_1.py
biotech/_status/monitors/05__file__/stasis/1_health.py
biotech/_status/monitors/05__file__/stasis/MODULES/MODULE_1.py
biotech/_status/monitors/05__file__/status_1.py
biotech/_status/monitors/06_various/stasis/1_health.py
biotech/_status/monitors/06_various/stasis/2_health.py
biotech-1.1.10.dist-info/METADATA
biotech-1.1.10.dist-info/WHEEL
biotech-1.1.10.dist-info/entry_points.txt
biotech-1.1.10.dist-info/RECORD
