Metadata-Version: 2.1
Name: biotech
Version: 1.1.10
Summary: A health monitoring stack
License: GPL-3.0-only
Keywords: alarms,screening,monitors,cybernetics,neurons,nervous system,bioelectric,homeostasis,reliability,consistency,integrity,guarantees,vows,oaths,assurances,insurances,ensurances,speed,calmness,education,augmentation,enhancement,improvements
Requires-Python: >=3.10,<4.0
Classifier: License :: OSI Approved :: GNU General Public License v3 (GPLv3)
Classifier: Programming Language :: Python :: 3
Classifier: Programming Language :: Python :: 3.10
Classifier: Programming Language :: Python :: 3.11
Classifier: Programming Language :: Python :: 3.12
Requires-Dist: body-scan (>=1.1.1,<2.0.0)
Requires-Dist: botanist (>=1.0.0,<2.0.0)
Requires-Dist: click (>=8.1.7,<9.0.0)
Requires-Dist: coverage (>=7.4.4,<8.0.0)
Requires-Dist: flask (>=3.0.3,<4.0.0)
Requires-Dist: mako (>=1.3.3,<2.0.0)
Requires-Dist: pexpect (>=4.9.0,<5.0.0)
Requires-Dist: pymongo (>=4.6.3,<5.0.0)
Requires-Dist: redis (>=5.0.3,<6.0.0)
Requires-Dist: requests (>=2.31.0,<3.0.0)
Requires-Dist: rich (>=13.7.1,<14.0.0)
Requires-Dist: sanic (>=23.12.1,<24.0.0)
Requires-Dist: tinydb (>=4.8.0,<5.0.0)
Project-URL: GitLab, https://gitlab.com/status600/climates/biotech
